yta_math/__init__.py
yta_math/graphic/__init__.py
yta_math/graphic/graphic.py
yta_math/graphic/graphic_axis.py
yta_math/graphic/node.py
yta_math/graphic/pair_of_nodes.py
yta_math/normalizable_value.py
yta_math/progression.py
yta_math/rate_functions/__init__.py
yta_math/rate_functions/rate_function.py
yta_math/rate_functions/rate_function_argument.py
yta_math/rate_functions/rate_function_graphic.py
yta_math/value_normalizer.py
yta_math-0.0.2.dist-info/licenses/LICENSE
yta_math-0.0.2.dist-info/METADATA
yta_math-0.0.2.dist-info/WHEEL
yta_math-0.0.2.dist-info/RECORD
